pathtree/__init__.py
pathtree/__main__.py
pathtree/cli.py
pathtree/pathtree.py
rlane_pathtree-1.0.3.dist-info/METADATA
rlane_pathtree-1.0.3.dist-info/WHEEL
rlane_pathtree-1.0.3.dist-info/entry_points.txt
rlane_pathtree-1.0.3.dist-info/licenses/LICENSE
rlane_pathtree-1.0.3.dist-info/RECORD
