Metadata-Version: 2.1
Name: rlane-pathtree
Version: 1.0.3
Summary: An os.PathLike wrapper around anytree.RenderTree
Keywords: python,pathtree
Author-Email: Russel Lane <russel@rlane.com>
License: MIT
Classifier: Development Status :: 4 - Beta
Classifier: Intended Audience :: Developers
Classifier: License :: OSI Approved :: MIT License
Classifier: Programming Language :: Python :: 3
Classifier: Topic :: Software Development :: Libraries :: Python Modules
Project-URL: Homepage, https://github.com/russellane/pathtree
Requires-Python: >=3.10
Requires-Dist: anytree>=2.12.1
Requires-Dist: argcomplete>=3.5.1
Requires-Dist: rlane-libcli>=1.0.8
Requires-Dist: termui>=0.0.1
Requires-Dist: tomli>=2.1.0
